lib_dzne_igblastn/__init__.py
lib_dzne_igblastn/_functions.py
lib_dzne_igblastn/_parsers.py
lib_dzne_igblastn-0.2.9.dist-info/LICENSE.txt
lib_dzne_igblastn-0.2.9.dist-info/METADATA
lib_dzne_igblastn-0.2.9.dist-info/WHEEL
lib_dzne_igblastn-0.2.9.dist-info/top_level.txt
lib_dzne_igblastn-0.2.9.dist-info/RECORD
