Metadata-Version: 2.1
Name: lib_dzne_igblastn
Version: 0.2.9
Summary: Libary for using igblastn. 
Author-email: Johannes <johannes-programming@posteo.org>
License: The MIT License (MIT)
Project-URL: Source, https://github.com/johannes-programming/lib_dzne_igblastn
Project-URL: Download, https://pypi.org/project/lib-dzne-igblastn/#files
Keywords: BASE,DZNE
Classifier: License :: OSI Approved :: MIT License
Classifier: Programming Language :: Python
Classifier: Programming Language :: Python :: 3
Requires-Python: >=3.11
License-File: LICENSE.txt
Requires-Dist: simple-tsv >=1.0
Requires-Dist: lib-dzne-filedata >=0.4.4
Requires-Dist: handle-igblastn >=0.1
